{"name": null, "description": null, "uuid": "0f30b6a9-cf36-46a7-b108-82d073317208", "data_format_version": "1.3.1", "components": [{"uuid": "648951d7-24fd-420a-ab77-c02c44170aa7", "name": "", "limit_type": "min", "__metadata__": {"fields": {"module": "gdm.distribution.limitset", "type": "VoltageLimitSet", "serialized_type": "base"}}, "value": {"value": 6.839579963954902, "units": "kilovolt", "__metadata__": {"fields": {"module": "gdm.quantities", "type": "PositiveVoltage", "serialized_type": "quantity"}}}}, {"uuid": "48890207-bb6a-448f-bb15-f1ebc023a787", "name": "", "limit_type": "max", "__metadata__": {"fields": {"module": "gdm.distribution.limitset", "type": "VoltageLimitSet", "serialized_type": "base"}}, "value": {"value": 7.559535749634366, "units": "kilovolt", "__metadata__": {"fields": {"module": "gdm.quantities", "type": "PositiveVoltage", "serialized_type": "quantity"}}}}, {"uuid": "4d66d438-5876-49aa-8cfe-9ecf889521e3", "name": "", "x": 36.60102672210813, "y": -120.91292875147646, "crs": null, "__metadata__": {"fields": {"module": "infrasys.location", "type": "Location", "serialized_type": "base"}}}, {"uuid": "ca0823b9-cd74-427d-93cb-85b316d3ce5b", "name": "p5rdt149-p5rhs0_1247x", "substation": null, "feeder": null, "voltage_type": "line-to-ground", "phases": ["A", "B", "C"], "__metadata__": {"fields": {"module": "gdm.distribution.components.distribution_bus", "type": "DistributionBus", "serialized_type": "base"}}, "voltagelimits": [{"__metadata__": {"fields": {"module": "gdm.distribution.limitset", "type": "VoltageLimitSet", "serialized_type": "composed_component", "uuid": "648951d7-24fd-420a-ab77-c02c44170aa7"}}}, {"__metadata__": {"fields": {"module": "gdm.distribution.limitset", "type": "VoltageLimitSet", "serialized_type": "composed_component", "uuid": "48890207-bb6a-448f-bb15-f1ebc023a787"}}}], "nominal_voltage": {"value": 7.199557856794634, "units": "kilovolt", "__metadata__": {"fields": {"module": "gdm.quantities", "type": "PositiveVoltage", "serialized_type": "quantity"}}}, "coordinate": {"__metadata__": {"fields": {"module": "infrasys.location", "type": "Location", "serialized_type": "composed_component", "uuid": "4d66d438-5876-49aa-8cfe-9ecf889521e3"}}}}, {"uuid": "7ee23e37-8acf-4a68-91ae-2d12050582a1", "name": "", "x": 36.59776619575616, "y": -120.91984825250762, "crs": null, "__metadata__": {"fields": {"module": "infrasys.location", "type": "Location", "serialized_type": "base"}}}, {"uuid": "e209c004-430d-4e95-9434-b35ced746012", "name": "p5rdt149-p5rhs0_1247x_b1_1", "substation": null, "feeder": null, "voltage_type": "line-to-ground", "phases": ["A", "B", "C"], "__metadata__": {"fields": {"module": "gdm.distribution.components.distribution_bus", "type": "DistributionBus", "serialized_type": "base"}}, "voltagelimits": [{"__metadata__": {"fields": {"module": "gdm.distribution.limitset", "type": "VoltageLimitSet", "serialized_type": "composed_component", "uuid": "648951d7-24fd-420a-ab77-c02c44170aa7"}}}, {"__metadata__": {"fields": {"module": "gdm.distribution.limitset", "type": "VoltageLimitSet", "serialized_type": "composed_component", "uuid": "48890207-bb6a-448f-bb15-f1ebc023a787"}}}], "nominal_voltage": {"value": 7.199557856794634, "units": "kilovolt", "__metadata__": {"fields": {"module": "gdm.quantities", "type": "PositiveVoltage", "serialized_type": "quantity"}}}, "coordinate": {"__metadata__": {"fields": {"module": "infrasys.location", "type": "Location", "serialized_type": "composed_component", "uuid": "7ee23e37-8acf-4a68-91ae-2d12050582a1"}}}}, {"uuid": "3dab1a1a-589d-4f0e-a445-eddafcd0f391", "name": "", "limit_type": "min", "__metadata__": {"fields": {"module": "gdm.distribution.limitset", "type": "VoltageLimitSet", "serialized_type": "base"}}, "value": {"value": 0.26327172275046934, "units": "kilovolt", "__metadata__": {"fields": {"module": "gdm.quantities", "type": "PositiveVoltage", "serialized_type": "quantity"}}}}, {"uuid": "9c796724-d5f3-4d21-b176-cbb84928779a", "name": "", "limit_type": "max", "__metadata__": {"fields": {"module": "gdm.distribution.limitset", "type": "VoltageLimitSet", "serialized_type": "base"}}, "value": {"value": 0.2909845356715714, "units": "kilovolt", "__metadata__": {"fields": {"module": "gdm.quantities", "type": "PositiveVoltage", "serialized_type": "quantity"}}}}, {"uuid": "7086ff95-7f93-40af-85ac-b5d9c682339d", "name": "", "x": 36.56885399412164, "y": -120.96155778160369, "crs": null, "__metadata__": {"fields": {"module": "infrasys.location", "type": "Location", "serialized_type": "base"}}}, {"uuid": "06f05f2e-cdf1-4fe9-8f51-0feda2f4368c", "name": "p5rdt149lv", "substation": null, "feeder": null, "voltage_type": "line-to-ground", "phases": ["A", "B", "C"], "__metadata__": {"fields": {"module": "gdm.distribution.components.distribution_bus", "type": "DistributionBus", "serialized_type": "base"}}, "voltagelimits": [{"__metadata__": {"fields": {"module": "gdm.distribution.limitset", "type": "VoltageLimitSet", "serialized_type": "composed_component", "uuid": "3dab1a1a-589d-4f0e-a445-eddafcd0f391"}}}, {"__metadata__": {"fields": {"module": "gdm.distribution.limitset", "type": "VoltageLimitSet", "serialized_type": "composed_component", "uuid": "9c796724-d5f3-4d21-b176-cbb84928779a"}}}], "nominal_voltage": {"value": 0.27712812921102037, "units": "kilovolt", "__metadata__": {"fields": {"module": "gdm.quantities", "type": "PositiveVoltage", "serialized_type": "quantity"}}}, "coordinate": {"__metadata__": {"fields": {"module": "infrasys.location", "type": "Location", "serialized_type": "composed_component", "uuid": "7086ff95-7f93-40af-85ac-b5d9c682339d"}}}}, {"uuid": "55616c82-43fc-4f7b-b472-6a1f1f3ab35a", "name": "", "x": 36.56884369179864, "y": -120.96150686468123, "crs": null, "__metadata__": {"fields": {"module": "infrasys.location", "type": "Location", "serialized_type": "base"}}}, {"uuid": "721d7c26-7914-4bc7-a638-26151f32c9ae", "name": "p5rlv265", "substation": null, "feeder": null, "voltage_type": "line-to-ground", "phases": ["A", "B", "C"], "__metadata__": {"fields": {"module": "gdm.distribution.components.distribution_bus", "type": "DistributionBus", "serialized_type": "base"}}, "voltagelimits": [{"__metadata__": {"fields": {"module": "gdm.distribution.limitset", "type": "VoltageLimitSet", "serialized_type": "composed_component", "uuid": "3dab1a1a-589d-4f0e-a445-eddafcd0f391"}}}, {"__metadata__": {"fields": {"module": "gdm.distribution.limitset", "type": "VoltageLimitSet", "serialized_type": "composed_component", "uuid": "9c796724-d5f3-4d21-b176-cbb84928779a"}}}], "nominal_voltage": {"value": 0.27712812921102037, "units": "kilovolt", "__metadata__": {"fields": {"module": "gdm.quantities", "type": "PositiveVoltage", "serialized_type": "quantity"}}}, "coordinate": {"__metadata__": {"fields": {"module": "infrasys.location", "type": "Location", "serialized_type": "composed_component", "uuid": "55616c82-43fc-4f7b-b472-6a1f1f3ab35a"}}}}, {"uuid": "37127d94-f28c-442d-b312-a0969660df5c", "name": "", "x": 36.588975013233814, "y": -120.97495604893834, "crs": null, "__metadata__": {"fields": {"module": "infrasys.location", "type": "Location", "serialized_type": "base"}}}, {"uuid": "06ee8228-1a86-4dea-a8a1-50f34a583cf7", "name": "p5rdt22lv", "substation": null, "feeder": null, "voltage_type": "line-to-ground", "phases": ["A", "B", "C"], "__metadata__": {"fields": {"module": "gdm.distribution.components.distribution_bus", "type": "DistributionBus", "serialized_type": "base"}}, "voltagelimits": [{"__metadata__": {"fields": {"module": "gdm.distribution.limitset", "type": "VoltageLimitSet", "serialized_type": "composed_component", "uuid": "3dab1a1a-589d-4f0e-a445-eddafcd0f391"}}}, {"__metadata__": {"fields": {"module": "gdm.distribution.limitset", "type": "VoltageLimitSet", "serialized_type": "composed_component", "uuid": "9c796724-d5f3-4d21-b176-cbb84928779a"}}}], "nominal_voltage": {"value": 0.27712812921102037, "units": "kilovolt", "__metadata__": {"fields": {"module": "gdm.quantities", "type": "PositiveVoltage", "serialized_type": "quantity"}}}, "coordinate": {"__metadata__": {"fields": {"module": "infrasys.location", "type": "Location", "serialized_type": "composed_component", "uuid": "37127d94-f28c-442d-b312-a0969660df5c"}}}}, {"uuid": "8bf19d52-571a-4c81-9de9-d157d8253776", "name": "", "x": 36.58898169475094, "y": -120.9749855407454, "crs": null, "__metadata__": {"fields": {"module": "infrasys.location", "type": "Location", "serialized_type": "base"}}}, {"uuid": "64ef1223-59e2-4f01-9aaa-e24640e177fb", "name": "p5rlv40", "substation": null, "feeder": null, "voltage_type": "line-to-ground", "phases": ["A", "B", "C"], "__metadata__": {"fields": {"module": "gdm.distribution.components.distribution_bus", "type": "DistributionBus", "serialized_type": "base"}}, "voltagelimits": [{"__metadata__": {"fields": {"module": "gdm.distribution.limitset", "type": "VoltageLimitSet", "serialized_type": "composed_component", "uuid": "3dab1a1a-589d-4f0e-a445-eddafcd0f391"}}}, {"__metadata__": {"fields": {"module": "gdm.distribution.limitset", "type": "VoltageLimitSet", "serialized_type": "composed_component", "uuid": "9c796724-d5f3-4d21-b176-cbb84928779a"}}}], "nominal_voltage": {"value": 0.27712812921102037, "units": "kilovolt", "__metadata__": {"fields": {"module": "gdm.quantities", "type": "PositiveVoltage", "serialized_type": "quantity"}}}, "coordinate": {"__metadata__": {"fields": {"module": "infrasys.location", "type": "Location", "serialized_type": "composed_component", "uuid": "8bf19d52-571a-4c81-9de9-d157d8253776"}}}}, {"uuid": "28f667d0-b51a-4b6c-8c24-791d6423ba54", "name": "", "x": 36.56887241444432, "y": -120.96160511254412, "crs": null, "__metadata__": {"fields": {"module": "infrasys.location", "type": "Location", "serialized_type": "base"}}}, {"uuid": "f6b25d9d-c603-41ca-b2c1-b16d4ecf7f11", "name": "p5rdt149", "substation": null, "feeder": null, "voltage_type": "line-to-ground", "phases": ["A", "B", "C"], "__metadata__": {"fields": {"module": "gdm.distribution.components.distribution_bus", "type": "DistributionBus", "serialized_type": "base"}}, "voltagelimits": [{"__metadata__": {"fields": {"module": "gdm.distribution.limitset", "type": "VoltageLimitSet", "serialized_type": "composed_component", "uuid": "648951d7-24fd-420a-ab77-c02c44170aa7"}}}, {"__metadata__": {"fields": {"module": "gdm.distribution.limitset", "type": "VoltageLimitSet", "serialized_type": "composed_component", "uuid": "48890207-bb6a-448f-bb15-f1ebc023a787"}}}], "nominal_voltage": {"value": 7.199557856794634, "units": "kilovolt", "__metadata__": {"fields": {"module": "gdm.quantities", "type": "PositiveVoltage", "serialized_type": "quantity"}}}, "coordinate": {"__metadata__": {"fields": {"module": "infrasys.location", "type": "Location", "serialized_type": "composed_component", "uuid": "28f667d0-b51a-4b6c-8c24-791d6423ba54"}}}}, {"uuid": "4f27fa68-c6ce-4d15-96d5-17bcfcdb0747", "name": "", "x": 36.584033672730996, "y": -120.97076724677004, "crs": null, "__metadata__": {"fields": {"module": "infrasys.location", "type": "Location", "serialized_type": "base"}}}, {"uuid": "cb266de1-74d5-4ac8-a50a-551e101934fa", "name": "p5rdt149-p5rdt22x", "substation": null, "feeder": null, "voltage_type": "line-to-ground", "phases": ["A", "B", "C"], "__metadata__": {"fields": {"module": "gdm.distribution.components.distribution_bus", "type": "DistributionBus", "serialized_type": "base"}}, "voltagelimits": [{"__metadata__": {"fields": {"module": "gdm.distribution.limitset", "type": "VoltageLimitSet", "serialized_type": "composed_component", "uuid": "648951d7-24fd-420a-ab77-c02c44170aa7"}}}, {"__metadata__": {"fields": {"module": "gdm.distribution.limitset", "type": "VoltageLimitSet", "serialized_type": "composed_component", "uuid": "48890207-bb6a-448f-bb15-f1ebc023a787"}}}], "nominal_voltage": {"value": 7.199557856794634, "units": "kilovolt", "__metadata__": {"fields": {"module": "gdm.quantities", "type": "PositiveVoltage", "serialized_type": "quantity"}}}, "coordinate": {"__metadata__": {"fields": {"module": "infrasys.location", "type": "Location", "serialized_type": "composed_component", "uuid": "4f27fa68-c6ce-4d15-96d5-17bcfcdb0747"}}}}, {"uuid": "2984f30f-329f-4b69-a35d-3b8ccc7a5577", "name": "", "x": 36.588933180522076, "y": -120.97494941278845, "crs": null, "__metadata__": {"fields": {"module": "infrasys.location", "type": "Location", "serialized_type": "base"}}}, {"uuid": "4d40a9f4-fcc9-403d-a5c6-6939e61614a7", "name": "p5rdt22", "substation": null, "feeder": null, "voltage_type": "line-to-ground", "phases": ["A", "B", "C"], "__metadata__": {"fields": {"module": "gdm.distribution.components.distribution_bus", "type": "DistributionBus", "serialized_type": "base"}}, "voltagelimits": [{"__metadata__": {"fields": {"module": "gdm.distribution.limitset", "type": "VoltageLimitSet", "serialized_type": "composed_component", "uuid": "648951d7-24fd-420a-ab77-c02c44170aa7"}}}, {"__metadata__": {"fields": {"module": "gdm.distribution.limitset", "type": "VoltageLimitSet", "serialized_type": "composed_component", "uuid": "48890207-bb6a-448f-bb15-f1ebc023a787"}}}], "nominal_voltage": {"value": 7.199557856794634, "units": "kilovolt", "__metadata__": {"fields": {"module": "gdm.quantities", "type": "PositiveVoltage", "serialized_type": "quantity"}}}, "coordinate": {"__metadata__": {"fields": {"module": "infrasys.location", "type": "Location", "serialized_type": "composed_component", "uuid": "2984f30f-329f-4b69-a35d-3b8ccc7a5577"}}}}, {"uuid": "64065470-2798-49c0-abc4-77ca0eefabba", "name": "", "x": 36.593633797608774, "y": -120.92580511661268, "crs": null, "__metadata__": {"fields": {"module": "infrasys.location", "type": "Location", "serialized_type": "base"}}}, {"uuid": "b842aa74-22f4-4b60-8627-7ea4e5b069f0", "name": "p5rdt149-p5rhs0_1247x_b2_1", "substation": null, "feeder": null, "voltage_type": "line-to-ground", "phases": ["A", "B", "C"], "__metadata__": {"fields": {"module": "gdm.distribution.components.distribution_bus", "type": "DistributionBus", "serialized_type": "base"}}, "voltagelimits": [{"__metadata__": {"fields": {"module": "gdm.distribution.limitset", "type": "VoltageLimitSet", "serialized_type": "composed_component", "uuid": "648951d7-24fd-420a-ab77-c02c44170aa7"}}}, {"__metadata__": {"fields": {"module": "gdm.distribution.limitset", "type": "VoltageLimitSet", "serialized_type": "composed_component", "uuid": "48890207-bb6a-448f-bb15-f1ebc023a787"}}}], "nominal_voltage": {"value": 7.199557856794634, "units": "kilovolt", "__metadata__": {"fields": {"module": "gdm.quantities", "type": "PositiveVoltage", "serialized_type": "quantity"}}}, "coordinate": {"__metadata__": {"fields": {"module": "infrasys.location", "type": "Location", "serialized_type": "composed_component", "uuid": "64065470-2798-49c0-abc4-77ca0eefabba"}}}}, {"uuid": "92f874ae-96df-4447-84f7-ffff6b3fcb9f", "name": "520dd9e6-8357-48f5-9fb2-55dbc8beea35_1", "__metadata__": {"fields": {"module": "gdm.distribution.equipment.phase_voltagesource_equipment", "type": "PhaseVoltageSourceEquipment", "serialized_type": "base"}}, "r0": {"value": 1e-05, "units": "ohm", "__metadata__": {"fields": {"module": "infrasys.quantities", "type": "Resistance", "serialized_type": "quantity"}}}, "r1": {"value": 1e-05, "units": "ohm", "__metadata__": {"fields": {"module": "infrasys.quantities", "type": "Resistance", "serialized_type": "quantity"}}}, "x0": {"value": 1e-05, "units": "ohm", "__metadata__": {"fields": {"module": "gdm.quantities", "type": "Reactance", "serialized_type": "quantity"}}}, "x1": {"value": 1e-05, "units": "ohm", "__metadata__": {"fields": {"module": "gdm.quantities", "type": "Reactance", "serialized_type": "quantity"}}}, "voltage": {"value": 7.415762124711317, "units": "kilovolt", "__metadata__": {"fields": {"module": "infrasys.quantities", "type": "Voltage", "serialized_type": "quantity"}}}, "angle": {"value": 0.0, "units": "degree", "__metadata__": {"fields": {"module": "infrasys.quantities", "type": "Angle", "serialized_type": "quantity"}}}}, {"uuid": "a8881cab-f225-4ebe-b898-46e28bc8b0f5", "name": "520dd9e6-8357-48f5-9fb2-55dbc8beea35_2", "__metadata__": {"fields": {"module": "gdm.distribution.equipment.phase_voltagesource_equipment", "type": "PhaseVoltageSourceEquipment", "serialized_type": "base"}}, "r0": {"value": 1e-05, "units": "ohm", "__metadata__": {"fields": {"module": "infrasys.quantities", "type": "Resistance", "serialized_type": "quantity"}}}, "r1": {"value": 1e-05, "units": "ohm", "__metadata__": {"fields": {"module": "infrasys.quantities", "type": "Resistance", "serialized_type": "quantity"}}}, "x0": {"value": 1e-05, "units": "ohm", "__metadata__": {"fields": {"module": "gdm.quantities", "type": "Reactance", "serialized_type": "quantity"}}}, "x1": {"value": 1e-05, "units": "ohm", "__metadata__": {"fields": {"module": "gdm.quantities", "type": "Reactance", "serialized_type": "quantity"}}}, "voltage": {"value": 7.415762124711317, "units": "kilovolt", "__metadata__": {"fields": {"module": "infrasys.quantities", "type": "Voltage", "serialized_type": "quantity"}}}, "angle": {"value": 120.0, "units": "degree", "__metadata__": {"fields": {"module": "infrasys.quantities", "type": "Angle", "serialized_type": "quantity"}}}}, {"uuid": "4f655964-f4d6-43f4-bcf3-76414ce0d515", "name": "520dd9e6-8357-48f5-9fb2-55dbc8beea35_3", "__metadata__": {"fields": {"module": "gdm.distribution.equipment.phase_voltagesource_equipment", "type": "PhaseVoltageSourceEquipment", "serialized_type": "base"}}, "r0": {"value": 1e-05, "units": "ohm", "__metadata__": {"fields": {"module": "infrasys.quantities", "type": "Resistance", "serialized_type": "quantity"}}}, "r1": {"value": 1e-05, "units": "ohm", "__metadata__": {"fields": {"module": "infrasys.quantities", "type": "Resistance", "serialized_type": "quantity"}}}, "x0": {"value": 1e-05, "units": "ohm", "__metadata__": {"fields": {"module": "gdm.quantities", "type": "Reactance", "serialized_type": "quantity"}}}, "x1": {"value": 1e-05, "units": "ohm", "__metadata__": {"fields": {"module": "gdm.quantities", "type": "Reactance", "serialized_type": "quantity"}}}, "voltage": {"value": 7.415762124711317, "units": "kilovolt", "__metadata__": {"fields": {"module": "infrasys.quantities", "type": "Voltage", "serialized_type": "quantity"}}}, "angle": {"value": 240.0, "units": "degree", "__metadata__": {"fields": {"module": "infrasys.quantities", "type": "Angle", "serialized_type": "quantity"}}}}, {"uuid": "82cca09b-c59f-463c-8019-eb4f9f16baf6", "name": "520dd9e6-8357-48f5-9fb2-55dbc8beea35", "__metadata__": {"fields": {"module": "gdm.distribution.equipment.voltagesource_equipment", "type": "VoltageSourceEquipment", "serialized_type": "base"}}, "sources": [{"__metadata__": {"fields": {"module": "gdm.distribution.equipment.phase_voltagesource_equipment", "type": "PhaseVoltageSourceEquipment", "serialized_type": "composed_component", "uuid": "92f874ae-96df-4447-84f7-ffff6b3fcb9f"}}}, {"__metadata__": {"fields": {"module": "gdm.distribution.equipment.phase_voltagesource_equipment", "type": "PhaseVoltageSourceEquipment", "serialized_type": "composed_component", "uuid": "a8881cab-f225-4ebe-b898-46e28bc8b0f5"}}}, {"__metadata__": {"fields": {"module": "gdm.distribution.equipment.phase_voltagesource_equipment", "type": "PhaseVoltageSourceEquipment", "serialized_type": "composed_component", "uuid": "4f655964-f4d6-43f4-bcf3-76414ce0d515"}}}]}, {"uuid": "29125d10-1167-40cb-9ab9-8dacbf0d8bef", "name": "source", "substation": null, "feeder": null, "phases": ["A", "B", "C"], "__metadata__": {"fields": {"module": "gdm.distribution.components.distribution_vsource", "type": "DistributionVoltageSource", "serialized_type": "base"}}, "bus": {"__metadata__": {"fields": {"module": "gdm.distribution.components.distribution_bus", "type": "DistributionBus", "serialized_type": "composed_component", "uuid": "ca0823b9-cd74-427d-93cb-85b316d3ce5b"}}}, "equipment": {"__metadata__": {"fields": {"module": "gdm.distribution.equipment.voltagesource_equipment", "type": "VoltageSourceEquipment", "serialized_type": "composed_component", "uuid": "82cca09b-c59f-463c-8019-eb4f9f16baf6"}}}}, {"uuid": "344a5b40-94c6-4e2b-b8cf-ce6d0352ecef", "name": "6493d6eb-60f2-429a-a659-006ce138bf8b_1", "z_real": 0.0, "z_imag": 0.0, "i_real": 0.0, "i_imag": 0.0, "p_real": 1.0, "p_imag": 1.0, "num_customers": null, "__metadata__": {"fields": {"module": "gdm.distribution.equipment.phase_load_equipment", "type": "PhaseLoadEquipment", "serialized_type": "base"}}, "real_power": {"value": 1.7112579411992943, "units": "kilowatt", "__metadata__": {"fields": {"module": "infrasys.quantities", "type": "ActivePower", "serialized_type": "quantity"}}}, "reactive_power": {"value": 0.39676444188146887, "units": "kilovar", "__metadata__": {"fields": {"module": "gdm.quantities", "type": "ReactivePower", "serialized_type": "quantity"}}}}, {"uuid": "077eaf06-34b1-469e-8975-9d678275e231", "name": "6493d6eb-60f2-429a-a659-006ce138bf8b_2", "z_real": 0.0, "z_imag": 0.0, "i_real": 0.0, "i_imag": 0.0, "p_real": 1.0, "p_imag": 1.0, "num_customers": null, "__metadata__": {"fields": {"module": "gdm.distribution.equipment.phase_load_equipment", "type": "PhaseLoadEquipment", "serialized_type": "base"}}, "real_power": {"value": 1.7112579411992943, "units": "kilowatt", "__metadata__": {"fields": {"module": "infrasys.quantities", "type": "ActivePower", "serialized_type": "quantity"}}}, "reactive_power": {"value": 0.39676444188146887, "units": "kilovar", "__metadata__": {"fields": {"module": "gdm.quantities", "type": "ReactivePower", "serialized_type": "quantity"}}}}, {"uuid": "c099ede6-696c-4456-bc21-daf9169b3302", "name": "6493d6eb-60f2-429a-a659-006ce138bf8b_3", "z_real": 0.0, "z_imag": 0.0, "i_real": 0.0, "i_imag": 0.0, "p_real": 1.0, "p_imag": 1.0, "num_customers": null, "__metadata__": {"fields": {"module": "gdm.distribution.equipment.phase_load_equipment", "type": "PhaseLoadEquipment", "serialized_type": "base"}}, "real_power": {"value": 1.7112579411992943, "units": "kilowatt", "__metadata__": {"fields": {"module": "infrasys.quantities", "type": "ActivePower", "serialized_type": "quantity"}}}, "reactive_power": {"value": 0.39676444188146887, "units": "kilovar", "__metadata__": {"fields": {"module": "gdm.quantities", "type": "ReactivePower", "serialized_type": "quantity"}}}}, {"uuid": "f816480b-4a4e-49d1-9896-e68e2281b135", "name": "e7eece81-b8e1-4963-8ea0-7a2498b06c8b", "connection_type": "STAR", "__metadata__": {"fields": {"module": "gdm.distribution.equipment.load_equipment", "type": "LoadEquipment", "serialized_type": "base"}}, "phase_loads": [{"__metadata__": {"fields": {"module": "gdm.distribution.equipment.phase_load_equipment", "type": "PhaseLoadEquipment", "serialized_type": "composed_component", "uuid": "344a5b40-94c6-4e2b-b8cf-ce6d0352ecef"}}}, {"__metadata__": {"fields": {"module": "gdm.distribution.equipment.phase_load_equipment", "type": "PhaseLoadEquipment", "serialized_type": "composed_component", "uuid": "077eaf06-34b1-469e-8975-9d678275e231"}}}, {"__metadata__": {"fields": {"module": "gdm.distribution.equipment.phase_load_equipment", "type": "PhaseLoadEquipment", "serialized_type": "composed_component", "uuid": "c099ede6-696c-4456-bc21-daf9169b3302"}}}]}, {"uuid": "bcee0b30-383e-485a-8602-f3d5702fd78b", "name": "load_p5rlv40", "substation": null, "feeder": null, "phases": ["A", "B", "C"], "__metadata__": {"fields": {"module": "gdm.distribution.components.distribution_load", "type": "DistributionLoad", "serialized_type": "base"}}, "bus": {"__metadata__": {"fields": {"module": "gdm.distribution.components.distribution_bus", "type": "DistributionBus", "serialized_type": "composed_component", "uuid": "64ef1223-59e2-4f01-9aaa-e24640e177fb"}}}, "equipment": {"__metadata__": {"fields": {"module": "gdm.distribution.equipment.load_equipment", "type": "LoadEquipment", "serialized_type": "composed_component", "uuid": "f816480b-4a4e-49d1-9896-e68e2281b135"}}}}, {"uuid": "376b0896-0823-4969-826f-e9acb92c3882", "name": "99027746-989e-48b7-bb85-7db49079ad8b_1", "z_real": 0.0, "z_imag": 0.0, "i_real": 0.0, "i_imag": 0.0, "p_real": 1.0, "p_imag": 1.0, "num_customers": null, "__metadata__": {"fields": {"module": "gdm.distribution.equipment.phase_load_equipment", "type": "PhaseLoadEquipment", "serialized_type": "base"}}, "real_power": {"value": 1.4061184464862206, "units": "kilowatt", "__metadata__": {"fields": {"module": "infrasys.quantities", "type": "ActivePower", "serialized_type": "quantity"}}}, "reactive_power": {"value": 0.3657795526143532, "units": "kilovar", "__metadata__": {"fields": {"module": "gdm.quantities", "type": "ReactivePower", "serialized_type": "quantity"}}}}, {"uuid": "f0167e0b-f90c-4a8f-b009-b551987ff449", "name": "99027746-989e-48b7-bb85-7db49079ad8b_2", "z_real": 0.0, "z_imag": 0.0, "i_real": 0.0, "i_imag": 0.0, "p_real": 1.0, "p_imag": 1.0, "num_customers": null, "__metadata__": {"fields": {"module": "gdm.distribution.equipment.phase_load_equipment", "type": "PhaseLoadEquipment", "serialized_type": "base"}}, "real_power": {"value": 1.4061184464862206, "units": "kilowatt", "__metadata__": {"fields": {"module": "infrasys.quantities", "type": "ActivePower", "serialized_type": "quantity"}}}, "reactive_power": {"value": 0.3657795526143532, "units": "kilovar", "__metadata__": {"fields": {"module": "gdm.quantities", "type": "ReactivePower", "serialized_type": "quantity"}}}}, {"uuid": "69ab5c16-81af-4d03-97c9-8b6d41f51d82", "name": "99027746-989e-48b7-bb85-7db49079ad8b_3", "z_real": 0.0, "z_imag": 0.0, "i_real": 0.0, "i_imag": 0.0, "p_real": 1.0, "p_imag": 1.0, "num_customers": null, "__metadata__": {"fields": {"module": "gdm.distribution.equipment.phase_load_equipment", "type": "PhaseLoadEquipment", "serialized_type": "base"}}, "real_power": {"value": 1.4061184464862206, "units": "kilowatt", "__metadata__": {"fields": {"module": "infrasys.quantities", "type": "ActivePower", "serialized_type": "quantity"}}}, "reactive_power": {"value": 0.3657795526143532, "units": "kilovar", "__metadata__": {"fields": {"module": "gdm.quantities", "type": "ReactivePower", "serialized_type": "quantity"}}}}, {"uuid": "223c2b1d-457b-4624-ab45-d38adfeda32c", "name": "19c582da-3fb8-43ea-93ee-a61d7536151d", "connection_type": "STAR", "__metadata__": {"fields": {"module": "gdm.distribution.equipment.load_equipment", "type": "LoadEquipment", "serialized_type": "base"}}, "phase_loads": [{"__metadata__": {"fields": {"module": "gdm.distribution.equipment.phase_load_equipment", "type": "PhaseLoadEquipment", "serialized_type": "composed_component", "uuid": "376b0896-0823-4969-826f-e9acb92c3882"}}}, {"__metadata__": {"fields": {"module": "gdm.distribution.equipment.phase_load_equipment", "type": "PhaseLoadEquipment", "serialized_type": "composed_component", "uuid": "f0167e0b-f90c-4a8f-b009-b551987ff449"}}}, {"__metadata__": {"fields": {"module": "gdm.distribution.equipment.phase_load_equipment", "type": "PhaseLoadEquipment", "serialized_type": "composed_component", "uuid": "69ab5c16-81af-4d03-97c9-8b6d41f51d82"}}}]}, {"uuid": "ff7ae363-d6ac-467d-bd97-83ee43344f06", "name": "load_p5rlv265", "substation": null, "feeder": null, "phases": ["A", "B", "C"], "__metadata__": {"fields": {"module": "gdm.distribution.components.distribution_load", "type": "DistributionLoad", "serialized_type": "base"}}, "bus": {"__metadata__": {"fields": {"module": "gdm.distribution.components.distribution_bus", "type": "DistributionBus", "serialized_type": "composed_component", "uuid": "721d7c26-7914-4bc7-a638-26151f32c9ae"}}}, "equipment": {"__metadata__": {"fields": {"module": "gdm.distribution.equipment.load_equipment", "type": "LoadEquipment", "serialized_type": "composed_component", "uuid": "223c2b1d-457b-4624-ab45-d38adfeda32c"}}}}, {"uuid": "8cc29ed7-5cd7-43ad-97d5-cb439eb76820", "name": "d0a192eb-539f-4de0-8a40-57ca5df63e00", "power_factor": 1.0, "__metadata__": {"fields": {"module": "gdm.distribution.controllers.distribution_inverter_controller", "type": "PowerfactorInverterController", "serialized_type": "base"}}}, {"uuid": "216050be-031c-400c-b8a8-a244a942e40a", "name": "05e7c3f5-c927-471a-bb68-50397926c0a7", "rise_limit": null, "fall_limit": null, "cutout_percent": 0.1, "cutin_percent": 0.1, "eff_curve": null, "__metadata__": {"fields": {"module": "gdm.distribution.equipment.inverter_equipment", "type": "InverterEquipment", "serialized_type": "base"}}, "capacity": {"value": 2.5, "units": "kilova", "__metadata__": {"fields": {"module": "gdm.quantities", "type": "PositiveApparentPower", "serialized_type": "quantity"}}}}, {"uuid": "2754c2d4-ab0e-4ff1-a9cf-856af3d22c85", "name": "pv_load_p5rlv40_inverter", "substation": null, "feeder": null, "__metadata__": {"fields": {"module": "gdm.distribution.components.distribution_inverter", "type": "DistrbutionInverter", "serialized_type": "base"}}, "controller": {"__metadata__": {"fields": {"module": "gdm.distribution.controllers.distribution_inverter_controller", "type": "PowerfactorInverterController", "serialized_type": "composed_component", "uuid": "8cc29ed7-5cd7-43ad-97d5-cb439eb76820"}}}, "equipment": {"__metadata__": {"fields": {"module": "gdm.distribution.equipment.inverter_equipment", "type": "InverterEquipment", "serialized_type": "composed_component", "uuid": "216050be-031c-400c-b8a8-a244a942e40a"}}}}, {"uuid": "f7de6bd7-c817-41c8-9522-2d380492256c", "name": "34f7b4c2-57c0-4a5f-8b57-fdb925a64237", "resistance": 50.0, "reactance": 0.0, "__metadata__": {"fields": {"module": "gdm.distribution.equipment.solar_equipment", "type": "SolarEquipment", "serialized_type": "base"}}, "rated_capacity": {"value": 2.5, "units": "kilova", "__metadata__": {"fields": {"module": "gdm.quantities", "type": "PositiveActivePower", "serialized_type": "quantity"}}}, "solar_power": {"value": 3.0, "units": "kilova", "__metadata__": {"fields": {"module": "gdm.quantities", "type": "PositiveActivePower", "serialized_type": "quantity"}}}}, {"uuid": "9a117acf-35df-4e9e-a376-a19651cd3733", "name": "pv_load_p5rlv40", "substation": null, "feeder": null, "phases": ["A", "B", "C"], "__metadata__": {"fields": {"module": "gdm.distribution.components.distribution_solar", "type": "DistributionSolar", "serialized_type": "base"}}, "bus": {"__metadata__": {"fields": {"module": "gdm.distribution.components.distribution_bus", "type": "DistributionBus", "serialized_type": "composed_component", "uuid": "64ef1223-59e2-4f01-9aaa-e24640e177fb"}}}, "inverter": {"__metadata__": {"fields": {"module": "gdm.distribution.components.distribution_inverter", "type": "DistrbutionInverter", "serialized_type": "composed_component", "uuid": "2754c2d4-ab0e-4ff1-a9cf-856af3d22c85"}}}, "equipment": {"__metadata__": {"fields": {"module": "gdm.distribution.equipment.solar_equipment", "type": "SolarEquipment", "serialized_type": "composed_component", "uuid": "f7de6bd7-c817-41c8-9522-2d380492256c"}}}}, {"uuid": "0014883a-aa84-4011-9214-e950283463e9", "name": "4bf58e95-2ac3-4289-8ed5-ccb62d6d1cdc", "power_factor": 1.0, "__metadata__": {"fields": {"module": "gdm.distribution.controllers.distribution_inverter_controller", "type": "PowerfactorInverterController", "serialized_type": "base"}}}, {"uuid": "1a7b6273-d0da-434e-9434-ec053c5a0962", "name": "8286f60c-cba0-436b-a382-f2882212d839", "rise_limit": null, "fall_limit": null, "cutout_percent": 0.1, "cutin_percent": 0.1, "eff_curve": null, "__metadata__": {"fields": {"module": "gdm.distribution.equipment.inverter_equipment", "type": "InverterEquipment", "serialized_type": "base"}}, "capacity": {"value": 2.5, "units": "kilova", "__metadata__": {"fields": {"module": "gdm.quantities", "type": "PositiveApparentPower", "serialized_type": "quantity"}}}}, {"uuid": "eb318831-1de0-430c-af51-306b1cf83ed0", "name": "pv_load_p5rlv40_1_inverter", "substation": null, "feeder": null, "__metadata__": {"fields": {"module": "gdm.distribution.components.distribution_inverter", "type": "DistrbutionInverter", "serialized_type": "base"}}, "controller": {"__metadata__": {"fields": {"module": "gdm.distribution.controllers.distribution_inverter_controller", "type": "PowerfactorInverterController", "serialized_type": "composed_component", "uuid": "0014883a-aa84-4011-9214-e950283463e9"}}}, "equipment": {"__metadata__": {"fields": {"module": "gdm.distribution.equipment.inverter_equipment", "type": "InverterEquipment", "serialized_type": "composed_component", "uuid": "1a7b6273-d0da-434e-9434-ec053c5a0962"}}}}, {"uuid": "fa628c16-fc80-4605-bcaa-3293ba864a81", "name": "bb686458-16ec-4653-aa1f-6cd6b6e6ffdf", "resistance": 50.0, "reactance": 0.0, "__metadata__": {"fields": {"module": "gdm.distribution.equipment.solar_equipment", "type": "SolarEquipment", "serialized_type": "base"}}, "rated_capacity": {"value": 2.5, "units": "kilova", "__metadata__": {"fields": {"module": "gdm.quantities", "type": "PositiveActivePower", "serialized_type": "quantity"}}}, "solar_power": {"value": 5.0, "units": "kilova", "__metadata__": {"fields": {"module": "gdm.quantities", "type": "PositiveActivePower", "serialized_type": "quantity"}}}}, {"uuid": "73064033-3247-4786-9c7b-8744e1c008cd", "name": "pv_load_p5rlv40_1", "substation": null, "feeder": null, "phases": ["A", "B", "C"], "__metadata__": {"fields": {"module": "gdm.distribution.components.distribution_solar", "type": "DistributionSolar", "serialized_type": "base"}}, "bus": {"__metadata__": {"fields": {"module": "gdm.distribution.components.distribution_bus", "type": "DistributionBus", "serialized_type": "composed_component", "uuid": "64ef1223-59e2-4f01-9aaa-e24640e177fb"}}}, "inverter": {"__metadata__": {"fields": {"module": "gdm.distribution.components.distribution_inverter", "type": "DistrbutionInverter", "serialized_type": "composed_component", "uuid": "eb318831-1de0-430c-af51-306b1cf83ed0"}}}, "equipment": {"__metadata__": {"fields": {"module": "gdm.distribution.equipment.solar_equipment", "type": "SolarEquipment", "serialized_type": "composed_component", "uuid": "fa628c16-fc80-4605-bcaa-3293ba864a81"}}}}, {"uuid": "500807a6-8c5e-46c2-87e7-90babd96fe2b", "name": "", "resistance": 0.87204, "is_grounded": false, "voltage_type": "line-to-ground", "num_phases": 3, "connection_type": "DELTA", "tap_positions": [1.0, 1.0, 1.0], "total_taps": 32, "min_tap_pu": 0.9, "max_tap_pu": 1.1, "__metadata__": {"fields": {"module": "gdm.distribution.equipment.distribution_transformer_equipment", "type": "WindingEquipment", "serialized_type": "base"}}, "nominal_voltage": {"value": 7.199769053117783, "units": "kilovolt", "__metadata__": {"fields": {"module": "gdm.quantities", "type": "PositiveVoltage", "serialized_type": "quantity"}}}, "rated_power": {"value": 75.0, "units": "kilova", "__metadata__": {"fields": {"module": "gdm.quantities", "type": "PositiveApparentPower", "serialized_type": "quantity"}}}}, {"uuid": "854fd34f-52e4-4030-bf65-85fa4bf9ee85", "name": "", "resistance": 0.87204, "is_grounded": false, "voltage_type": "line-to-ground", "num_phases": 3, "connection_type": "STAR", "tap_positions": [1.0, 1.0, 1.0], "total_taps": 32, "min_tap_pu": 0.9, "max_tap_pu": 1.1, "__metadata__": {"fields": {"module": "gdm.distribution.equipment.distribution_transformer_equipment", "type": "WindingEquipment", "serialized_type": "base"}}, "nominal_voltage": {"value": 0.27713625866050806, "units": "kilovolt", "__metadata__": {"fields": {"module": "gdm.quantities", "type": "PositiveVoltage", "serialized_type": "quantity"}}}, "rated_power": {"value": 75.0, "units": "kilova", "__metadata__": {"fields": {"module": "gdm.quantities", "type": "PositiveApparentPower", "serialized_type": "quantity"}}}}, {"uuid": "695e324d-6048-45ad-8234-e0f14cc6c926", "name": "a2ec7764-bdde-4d00-8204-85bfc3f380ce", "pct_no_load_loss": 0.6, "pct_full_load_loss": 1.74408, "coupling_sequences": [[1, 2]], "winding_reactances": [3.24], "is_center_tapped": false, "__metadata__": {"fields": {"module": "gdm.distribution.equipment.distribution_transformer_equipment", "type": "DistributionTransformerEquipment", "serialized_type": "base"}}, "windings": [{"__metadata__": {"fields": {"module": "gdm.distribution.equipment.distribution_transformer_equipment", "type": "WindingEquipment", "serialized_type": "composed_component", "uuid": "500807a6-8c5e-46c2-87e7-90babd96fe2b"}}}, {"__metadata__": {"fields": {"module": "gdm.distribution.equipment.distribution_transformer_equipment", "type": "WindingEquipment", "serialized_type": "composed_component", "uuid": "854fd34f-52e4-4030-bf65-85fa4bf9ee85"}}}]}, {"uuid": "e5fe03b5-8ff0-4ae8-a45c-37dc3e0eef2e", "name": "tr(r:p5rdt149-p5rdt149lv)", "substation": null, "feeder": null, "winding_phases": [["A", "B", "C"], ["A", "B", "C"]], "__metadata__": {"fields": {"module": "gdm.distribution.components.distribution_transformer", "type": "DistributionTransformer", "serialized_type": "base"}}, "buses": [{"__metadata__": {"fields": {"module": "gdm.distribution.components.distribution_bus", "type": "DistributionBus", "serialized_type": "composed_component", "uuid": "f6b25d9d-c603-41ca-b2c1-b16d4ecf7f11"}}}, {"__metadata__": {"fields": {"module": "gdm.distribution.components.distribution_bus", "type": "DistributionBus", "serialized_type": "composed_component", "uuid": "06f05f2e-cdf1-4fe9-8f51-0feda2f4368c"}}}], "equipment": {"__metadata__": {"fields": {"module": "gdm.distribution.equipment.distribution_transformer_equipment", "type": "DistributionTransformerEquipment", "serialized_type": "composed_component", "uuid": "695e324d-6048-45ad-8234-e0f14cc6c926"}}}}, {"uuid": "f65a6e97-8128-4039-a76a-66a65a48edf2", "name": "tr(r:p5rdt22-p5rdt22lv)", "substation": null, "feeder": null, "winding_phases": [["A", "B", "C"], ["A", "B", "C"]], "__metadata__": {"fields": {"module": "gdm.distribution.components.distribution_transformer", "type": "DistributionTransformer", "serialized_type": "base"}}, "buses": [{"__metadata__": {"fields": {"module": "gdm.distribution.components.distribution_bus", "type": "DistributionBus", "serialized_type": "composed_component", "uuid": "4d40a9f4-fcc9-403d-a5c6-6939e61614a7"}}}, {"__metadata__": {"fields": {"module": "gdm.distribution.components.distribution_bus", "type": "DistributionBus", "serialized_type": "composed_component", "uuid": "06ee8228-1a86-4dea-a8a1-50f34a583cf7"}}}], "equipment": {"__metadata__": {"fields": {"module": "gdm.distribution.equipment.distribution_transformer_equipment", "type": "DistributionTransformerEquipment", "serialized_type": "composed_component", "uuid": "695e324d-6048-45ad-8234-e0f14cc6c926"}}}}, {"uuid": "30444b0b-8a5c-4fa9-a099-6be95db36e95", "name": "", "limit_type": "max", "__metadata__": {"fields": {"module": "gdm.distribution.limitset", "type": "ThermalLimitSet", "serialized_type": "base"}}, "value": {"value": 600.0, "units": "ampere", "__metadata__": {"fields": {"module": "gdm.quantities", "type": "PositiveCurrent", "serialized_type": "quantity"}}}}, {"uuid": "6a813cd5-5524-438a-afd5-43b599f3c0ec", "name": "e01c502d-77e1-49aa-8e73-b72fe287cd20", "controller": null, "__metadata__": {"fields": {"module": "gdm.distribution.equipment.matrix_impedance_switch_equipment", "type": "MatrixImpedanceSwitchEquipment", "serialized_type": "base"}}, "r_matrix": {"value": [[1.0, 0.0, 0.0], [0.0, 1.0, 0.0], [0.0, 0.0, 1.0]], "units": "ohm / meter", "__metadata__": {"fields": {"module": "gdm.quantities", "type": "ResistancePULength", "serialized_type": "quantity"}}}, "x_matrix": {"value": [[1.0, 0.0, 0.0], [0.0, 1.0, 0.0], [0.0, 0.0, 1.0]], "units": "ohm / meter", "__metadata__": {"fields": {"module": "gdm.quantities", "type": "ReactancePULength", "serialized_type": "quantity"}}}, "c_matrix": {"value": [[1.0666666666666667, -0.03333333333333331, -0.03333333333333331], [-0.03333333333333331, 1.0666666666666667, -0.03333333333333331], [-0.03333333333333331, -0.03333333333333331, 1.0666666666666667]], "units": "nanofarad / meter", "__metadata__": {"fields": {"module": "gdm.quantities", "type": "CapacitancePULength", "serialized_type": "quantity"}}}, "ampacity": {"value": 325.0, "units": "ampere", "__metadata__": {"fields": {"module": "gdm.quantities", "type": "PositiveCurrent", "serialized_type": "quantity"}}}, "loading_limit": {"__metadata__": {"fields": {"module": "gdm.distribution.limitset", "type": "ThermalLimitSet", "serialized_type": "composed_component", "uuid": "30444b0b-8a5c-4fa9-a099-6be95db36e95"}}}}, {"uuid": "9168e8d4-1df0-42fb-b73e-b4783b2a2b6b", "name": "3p_oh_al_acsr_4/0_penguin_3", "__metadata__": {"fields": {"module": "gdm.distribution.equipment.matrix_impedance_branch_equipment", "type": "MatrixImpedanceBranchEquipment", "serialized_type": "base"}}, "r_matrix": {"value": [[0.3635667, 0.09006667, 0.09006667], [0.09006667, 0.3635667, 0.09006667], [0.09006667, 0.09006667, 0.3635667]], "units": "ohm / kilometer", "__metadata__": {"fields": {"module": "gdm.quantities", "type": "ResistancePULength", "serialized_type": "quantity"}}}, "x_matrix": {"value": [[0.6385333, 0.2202333, 0.2202333], [0.2202333, 0.6385333, 0.2202333], [0.2202333, 0.2202333, 0.6385333]], "units": "ohm / kilometer", "__metadata__": {"fields": {"module": "gdm.quantities", "type": "ReactancePULength", "serialized_type": "quantity"}}}, "c_matrix": {"value": [[7.448267, -3.1846329999999994, -3.1846329999999994], [-3.1846329999999994, 7.448267, -3.1846329999999994], [-3.1846329999999994, -3.1846329999999994, 7.448267]], "units": "nanofarad / kilometer", "__metadata__": {"fields": {"module": "gdm.quantities", "type": "CapacitancePULength", "serialized_type": "quantity"}}}, "ampacity": {"value": 325.0, "units": "ampere", "__metadata__": {"fields": {"module": "gdm.quantities", "type": "PositiveCurrent", "serialized_type": "quantity"}}}, "loading_limit": {"__metadata__": {"fields": {"module": "gdm.distribution.limitset", "type": "ThermalLimitSet", "serialized_type": "composed_component", "uuid": "30444b0b-8a5c-4fa9-a099-6be95db36e95"}}}}, {"uuid": "9b70d203-a28a-4d55-be70-21d0a61ccbe3", "name": "3p_ug_al_3", "__metadata__": {"fields": {"module": "gdm.distribution.equipment.matrix_impedance_branch_equipment", "type": "MatrixImpedanceBranchEquipment", "serialized_type": "base"}}, "r_matrix": {"value": [[0.445, 0.1745, 0.1745], [0.1745, 0.445, 0.1745], [0.1745, 0.1745, 0.445]], "units": "ohm / kilometer", "__metadata__": {"fields": {"module": "gdm.quantities", "type": "ResistancePULength", "serialized_type": "quantity"}}}, "x_matrix": {"value": [[0.5326, 0.2912, 0.2912], [0.2912, 0.5326, 0.2912], [0.2912, 0.2912, 0.5326]], "units": "ohm / kilometer", "__metadata__": {"fields": {"module": "gdm.quantities", "type": "ReactancePULength", "serialized_type": "quantity"}}}, "c_matrix": {"value": [[145.291, -72.088, -72.088], [-72.088, 145.291, -72.088], [-72.088, -72.088, 145.291]], "units": "nanofarad / kilometer", "__metadata__": {"fields": {"module": "gdm.quantities", "type": "CapacitancePULength", "serialized_type": "quantity"}}}, "ampacity": {"value": 285.0, "units": "ampere", "__metadata__": {"fields": {"module": "gdm.quantities", "type": "PositiveCurrent", "serialized_type": "quantity"}}}, "loading_limit": {"__metadata__": {"fields": {"module": "gdm.distribution.limitset", "type": "ThermalLimitSet", "serialized_type": "composed_component", "uuid": "30444b0b-8a5c-4fa9-a099-6be95db36e95"}}}}, {"uuid": "b9d5538b-452c-493e-bd10-76e0bc7f0f58", "name": "l(r:p5rdt149-p5rhs0_1247)", "substation": null, "feeder": null, "phases": ["A", "B", "C"], "__metadata__": {"fields": {"module": "gdm.distribution.components.matrix_impedance_branch", "type": "MatrixImpedanceBranch", "serialized_type": "base"}}, "buses": [{"__metadata__": {"fields": {"module": "gdm.distribution.components.distribution_bus", "type": "DistributionBus", "serialized_type": "composed_component", "uuid": "ca0823b9-cd74-427d-93cb-85b316d3ce5b"}}}, {"__metadata__": {"fields": {"module": "gdm.distribution.components.distribution_bus", "type": "DistributionBus", "serialized_type": "composed_component", "uuid": "e209c004-430d-4e95-9434-b35ced746012"}}}], "length": {"value": 0.561451, "units": "kilometer", "__metadata__": {"fields": {"module": "gdm.quantities", "type": "PositiveDistance", "serialized_type": "quantity"}}}, "equipment": {"__metadata__": {"fields": {"module": "gdm.distribution.equipment.matrix_impedance_branch_equipment", "type": "MatrixImpedanceBranchEquipment", "serialized_type": "composed_component", "uuid": "9168e8d4-1df0-42fb-b73e-b4783b2a2b6b"}}}}, {"uuid": "e9bef612-1e07-4b69-a8ba-01a5524ab33e", "name": "l(r:p5rdt149lv-p5rlv265)", "substation": null, "feeder": null, "phases": ["A", "B", "C"], "__metadata__": {"fields": {"module": "gdm.distribution.components.matrix_impedance_branch", "type": "MatrixImpedanceBranch", "serialized_type": "base"}}, "buses": [{"__metadata__": {"fields": {"module": "gdm.distribution.components.distribution_bus", "type": "DistributionBus", "serialized_type": "composed_component", "uuid": "06f05f2e-cdf1-4fe9-8f51-0feda2f4368c"}}}, {"__metadata__": {"fields": {"module": "gdm.distribution.components.distribution_bus", "type": "DistributionBus", "serialized_type": "composed_component", "uuid": "721d7c26-7914-4bc7-a638-26151f32c9ae"}}}], "length": {"value": 0.001, "units": "kilometer", "__metadata__": {"fields": {"module": "gdm.quantities", "type": "PositiveDistance", "serialized_type": "quantity"}}}, "equipment": {"__metadata__": {"fields": {"module": "gdm.distribution.equipment.matrix_impedance_branch_equipment", "type": "MatrixImpedanceBranchEquipment", "serialized_type": "composed_component", "uuid": "9b70d203-a28a-4d55-be70-21d0a61ccbe3"}}}}, {"uuid": "4c5324e8-c3ff-4273-a5c6-1128f08f3361", "name": "l(r:p5rdt22lv-p5rlv40)", "substation": null, "feeder": null, "phases": ["A", "B", "C"], "__metadata__": {"fields": {"module": "gdm.distribution.components.matrix_impedance_branch", "type": "MatrixImpedanceBranch", "serialized_type": "base"}}, "buses": [{"__metadata__": {"fields": {"module": "gdm.distribution.components.distribution_bus", "type": "DistributionBus", "serialized_type": "composed_component", "uuid": "06ee8228-1a86-4dea-a8a1-50f34a583cf7"}}}, {"__metadata__": {"fields": {"module": "gdm.distribution.components.distribution_bus", "type": "DistributionBus", "serialized_type": "composed_component", "uuid": "64ef1223-59e2-4f01-9aaa-e24640e177fb"}}}], "length": {"value": 0.004450080000000001, "units": "kilometer", "__metadata__": {"fields": {"module": "gdm.quantities", "type": "PositiveDistance", "serialized_type": "quantity"}}}, "equipment": {"__metadata__": {"fields": {"module": "gdm.distribution.equipment.matrix_impedance_branch_equipment", "type": "MatrixImpedanceBranchEquipment", "serialized_type": "composed_component", "uuid": "9b70d203-a28a-4d55-be70-21d0a61ccbe3"}}}}, {"uuid": "ee459172-4407-4112-b4b7-81bba1b153dd", "name": "l(r:p5rdt149-p5rdt22)_s0", "substation": null, "feeder": null, "phases": ["A", "B", "C"], "__metadata__": {"fields": {"module": "gdm.distribution.components.matrix_impedance_branch", "type": "MatrixImpedanceBranch", "serialized_type": "base"}}, "buses": [{"__metadata__": {"fields": {"module": "gdm.distribution.components.distribution_bus", "type": "DistributionBus", "serialized_type": "composed_component", "uuid": "f6b25d9d-c603-41ca-b2c1-b16d4ecf7f11"}}}, {"__metadata__": {"fields": {"module": "gdm.distribution.components.distribution_bus", "type": "DistributionBus", "serialized_type": "composed_component", "uuid": "cb266de1-74d5-4ac8-a50a-551e101934fa"}}}], "length": {"value": 0.829829, "units": "kilometer", "__metadata__": {"fields": {"module": "gdm.quantities", "type": "PositiveDistance", "serialized_type": "quantity"}}}, "equipment": {"__metadata__": {"fields": {"module": "gdm.distribution.equipment.matrix_impedance_branch_equipment", "type": "MatrixImpedanceBranchEquipment", "serialized_type": "composed_component", "uuid": "9168e8d4-1df0-42fb-b73e-b4783b2a2b6b"}}}}, {"uuid": "75698671-398f-419c-a0b7-304a2dc3540b", "name": "l(r:p5rdt149-p5rdt22)_s1", "substation": null, "feeder": null, "phases": ["A", "B", "C"], "__metadata__": {"fields": {"module": "gdm.distribution.components.matrix_impedance_branch", "type": "MatrixImpedanceBranch", "serialized_type": "base"}}, "buses": [{"__metadata__": {"fields": {"module": "gdm.distribution.components.distribution_bus", "type": "DistributionBus", "serialized_type": "composed_component", "uuid": "cb266de1-74d5-4ac8-a50a-551e101934fa"}}}, {"__metadata__": {"fields": {"module": "gdm.distribution.components.distribution_bus", "type": "DistributionBus", "serialized_type": "composed_component", "uuid": "4d40a9f4-fcc9-403d-a5c6-6939e61614a7"}}}], "length": {"value": 1.87473, "units": "kilometer", "__metadata__": {"fields": {"module": "gdm.quantities", "type": "PositiveDistance", "serialized_type": "quantity"}}}, "equipment": {"__metadata__": {"fields": {"module": "gdm.distribution.equipment.matrix_impedance_branch_equipment", "type": "MatrixImpedanceBranchEquipment", "serialized_type": "composed_component", "uuid": "9168e8d4-1df0-42fb-b73e-b4783b2a2b6b"}}}}, {"uuid": "484f3c06-e002-461b-9663-3bf94e8b991f", "name": "l(r:p5rdt149-p5rhs0_1247)_disconnect", "substation": null, "feeder": null, "phases": ["A", "B", "C"], "is_closed": [true, true, true], "__metadata__": {"fields": {"module": "gdm.distribution.components.matrix_impedance_switch", "type": "MatrixImpedanceSwitch", "serialized_type": "base"}}, "buses": [{"__metadata__": {"fields": {"module": "gdm.distribution.components.distribution_bus", "type": "DistributionBus", "serialized_type": "composed_component", "uuid": "e209c004-430d-4e95-9434-b35ced746012"}}}, {"__metadata__": {"fields": {"module": "gdm.distribution.components.distribution_bus", "type": "DistributionBus", "serialized_type": "composed_component", "uuid": "b842aa74-22f4-4b60-8627-7ea4e5b069f0"}}}], "length": {"value": 0.001, "units": "meter", "__metadata__": {"fields": {"module": "gdm.quantities", "type": "PositiveDistance", "serialized_type": "quantity"}}}, "equipment": {"__metadata__": {"fields": {"module": "gdm.distribution.equipment.matrix_impedance_switch_equipment", "type": "MatrixImpedanceSwitchEquipment", "serialized_type": "composed_component", "uuid": "6a813cd5-5524-438a-afd5-43b599f3c0ec"}}}}, {"uuid": "fef327cb-9f62-4e7a-8952-3f31caf05f83", "name": "l(r:p5rdt149-p5rhs0_1247)_cont", "substation": null, "feeder": null, "phases": ["A", "B", "C"], "__metadata__": {"fields": {"module": "gdm.distribution.components.matrix_impedance_branch", "type": "MatrixImpedanceBranch", "serialized_type": "base"}}, "buses": [{"__metadata__": {"fields": {"module": "gdm.distribution.components.distribution_bus", "type": "DistributionBus", "serialized_type": "composed_component", "uuid": "b842aa74-22f4-4b60-8627-7ea4e5b069f0"}}}, {"__metadata__": {"fields": {"module": "gdm.distribution.components.distribution_bus", "type": "DistributionBus", "serialized_type": "composed_component", "uuid": "f6b25d9d-c603-41ca-b2c1-b16d4ecf7f11"}}}], "length": {"value": 5.0620590000000005, "units": "kilometer", "__metadata__": {"fields": {"module": "gdm.quantities", "type": "PositiveDistance", "serialized_type": "quantity"}}}, "equipment": {"__metadata__": {"fields": {"module": "gdm.distribution.equipment.matrix_impedance_branch_equipment", "type": "MatrixImpedanceBranchEquipment", "serialized_type": "composed_component", "uuid": "9168e8d4-1df0-42fb-b73e-b4783b2a2b6b"}}}}], "time_series": {"directory": "p5r_time_series"}}